s3blobsync/__init__.py
s3blobsync/download_blob.py
s3blobsync/download_s3.py
s3blobsync/list_s3.py
s3blobsync/s3blobsync.py
s3blobsync/lib/__init__.py
s3blobsync/lib/blob.py
s3blobsync/lib/common.py
s3blobsync/lib/s3.py
s3blobsync-1.3.dist-info/METADATA
s3blobsync-1.3.dist-info/WHEEL
s3blobsync-1.3.dist-info/entry_points.txt
s3blobsync-1.3.dist-info/top_level.txt
s3blobsync-1.3.dist-info/RECORD
