Metadata-Version: 2.1
Name: s3blobsync
Version: 1.3
Summary: Provides a seamless way to operate between AWS S3 and Azure Blob Storage
Home-page: https://github.com/admenergy/s3blobsync
Author: Ala Arab
Author-email: ala.arab@admenergy.com
Classifier: Programming Language :: Python :: 3
Classifier: License :: OSI Approved :: MIT License
Classifier: Operating System :: OS Independent
Requires-Python: >=3.10
Requires-Dist: boto3
Requires-Dist: azure-storage-blob
Requires-Dist: tqdm
Requires-Dist: python-dotenv
